{
    "sourceFile": "src/App.tsx",
    "activeCommit": 0,
    "commits": [
        {
            "activePatchIndex": 12,
            "patches": [
                {
                    "date": 1712675009174,
                    "content": "Index: \n===================================================================\n--- \n+++ \n"
                },
                {
                    "date": 1712675014451,
                    "content": "Index: \n===================================================================\n--- \n+++ \n@@ -0,0 +1,45 @@\n+import React from 'react';\n+import 'bulma/css/bulma.css';\n+import '@fortawesome/fontawesome-free/css/all.css';\n+import './App.scss';\n+import { TabContent } from './components/TabContent/TabContent';\n+\n+export const tabs = [\n+  { id: 'tab-1', title: 'Tab 1', content: 'Some text 1' },\n+  { id: 'tab-2', title: 'Tab 2', content: 'Some text 2' },\n+  { id: 'tab-3', title: 'Tab 3', content: 'Some text 3' },\n+];\n+\n+export const App: React.FC = () => {\n+  return (\n+    <div className=\"section\">\n+      <h1 className=\"title\">Selected tab is Tab 1</h1>\n+\n+      <div data-cy=\"TabsComponent\">\n+        <div className=\"tabs is-boxed\">\n+          <ul>\n+            <li className=\"is-active\" data-cy=\"Tab\">\n+              <a href=\"#tab-1\" data-cy=\"TabLink\">\n+                Tab 1\n+              </a>\n+            </li>\n+\n+            <li data-cy=\"Tab\">\n+              <a href=\"#tab-2\" data-cy=\"TabLink\">\n+                Tab 2\n+              </a>\n+            </li>\n+\n+            <li data-cy=\"Tab\">\n+              <a href=\"#tab-3\" data-cy=\"TabLink\">\n+                Tab 3\n+              </a>\n+            </li>\n+          </ul>\n+        </div>\n+\n+        <TabContent \n+      </div>\n+    </div>\n+  );\n+};\n"
                },
                {
                    "date": 1712675019663,
                    "content": "Index: \n===================================================================\n--- \n+++ \n@@ -0,0 +1,44 @@\n+import React from 'react';\n+import 'bulma/css/bulma.css';\n+import '@fortawesome/fontawesome-free/css/all.css';\n+import './App.scss';\n+import { TabContent } from './components/TabContent/TabContent';\n+\n+export const tabs = [\n+  { id: 'tab-1', title: 'Tab 1', content: 'Some text 1' },\n+  { id: 'tab-2', title: 'Tab 2', content: 'Some text 2' },\n+  { id: 'tab-3', title: 'Tab 3', content: 'Some text 3' },\n+];\n+\n+export const App: React.FC = () => {\n+  return (\n+    <div className=\"section\">\n+      <h1 className=\"title\">Selected tab is Tab 1</h1>\n+\n+      <div data-cy=\"TabsComponent\">\n+        <div className=\"tabs is-boxed\">\n+          <ul>\n+            <li className=\"is-active\" data-cy=\"Tab\">\n+              <a href=\"#tab-1\" data-cy=\"TabLink\">\n+                Tab 1\n+              </a>\n+            </li>\n+\n+            <li data-cy=\"Tab\">\n+              <a href=\"#tab-2\" data-cy=\"TabLink\">\n+                Tab 2\n+              </a>\n+            </li>\n+\n+            <li data-cy=\"Tab\">\n+              <a href=\"#tab-3\" data-cy=\"TabLink\">\n+                Tab 3\n+              </a>\n+            </li>\n+          </ul>\n+        </div>\n+        <TabContent />\n+      </div>\n+    </div>\n+  );\n+};\n"
                },
                {
                    "date": 1712675031135,
                    "content": "Index: \n===================================================================\n--- \n+++ \n@@ -0,0 +1,45 @@\n+import React from 'react';\n+import 'bulma/css/bulma.css';\n+import '@fortawesome/fontawesome-free/css/all.css';\n+import './App.scss';\n+import { TabContent } from './components/TabContent/TabContent';\n+\n+export const tabs = [\n+  { id: 'tab-1', title: 'Tab 1', content: 'Some text 1' },\n+  { id: 'tab-2', title: 'Tab 2', content: 'Some text 2' },\n+  { id: 'tab-3', title: 'Tab 3', content: 'Some text 3' },\n+];\n+\n+export const App: React.FC = () => {\n+  return (\n+    <div className=\"section\">\n+      <h1 className=\"title\">Selected tab is Tab 1</h1>\n+\n+      <div data-cy=\"TabsComponent\">\n+        <div className=\"tabs is-boxed\">\n+          <ul>\n+            <li className=\"is-active\" data-cy=\"Tab\">\n+              <a href=\"#tab-1\" data-cy=\"TabLink\">\n+                Tab 1\n+              </a>\n+            </li>\n+\n+            <li data-cy=\"Tab\">\n+              <a href=\"#tab-2\" data-cy=\"TabLink\">\n+                Tab 2\n+              </a>\n+            </li>\n+\n+            <li data-cy=\"Tab\">\n+              <a href=\"#tab-3\" data-cy=\"TabLink\">\n+                Tab 3\n+              </a>\n+            </li>\n+          </ul>\n+        </div>\n+\n+        <TabContent />\n+      </div>\n+    </div>\n+  );\n+};\n"
                },
                {
                    "date": 1712675040888,
                    "content": "Index: \n===================================================================\n--- \n+++ \n@@ -2,8 +2,9 @@\n import 'bulma/css/bulma.css';\n import '@fortawesome/fontawesome-free/css/all.css';\n import './App.scss';\n import { TabContent } from './components/TabContent/TabContent';\n+impo\n \n export const tabs = [\n   { id: 'tab-1', title: 'Tab 1', content: 'Some text 1' },\n   { id: 'tab-2', title: 'Tab 2', content: 'Some text 2' },\n@@ -36,143 +37,9 @@\n               </a>\n             </li>\n           </ul>\n         </div>\n-\n         <TabContent />\n       </div>\n     </div>\n   );\n };\n-import React from 'react';\n-import 'bulma/css/bulma.css';\n-import '@fortawesome/fontawesome-free/css/all.css';\n-import './App.scss';\n-import { TabContent } from './components/TabContent/TabContent';\n-\n-export const tabs = [\n-  { id: 'tab-1', title: 'Tab 1', content: 'Some text 1' },\n-  { id: 'tab-2', title: 'Tab 2', content: 'Some text 2' },\n-  { id: 'tab-3', title: 'Tab 3', content: 'Some text 3' },\n-];\n-\n-export const App: React.FC = () => {\n-  return (\n-    <div className=\"section\">\n-      <h1 className=\"title\">Selected tab is Tab 1</h1>\n-\n-      <div data-cy=\"TabsComponent\">\n-        <div className=\"tabs is-boxed\">\n-          <ul>\n-            <li className=\"is-active\" data-cy=\"Tab\">\n-              <a href=\"#tab-1\" data-cy=\"TabLink\">\n-                Tab 1\n-              </a>\n-            </li>\n-\n-            <li data-cy=\"Tab\">\n-              <a href=\"#tab-2\" data-cy=\"TabLink\">\n-                Tab 2\n-              </a>\n-            </li>\n-\n-            <li data-cy=\"Tab\">\n-              <a href=\"#tab-3\" data-cy=\"TabLink\">\n-                Tab 3\n-              </a>\n-            </li>\n-          </ul>\n-        </div>\n-        <TabContent />\n-      </div>\n-    </div>\n-  );\n-};\n-import React from 'react';\n-import 'bulma/css/bulma.css';\n-import '@fortawesome/fontawesome-free/css/all.css';\n-import './App.scss';\n-import { TabContent } from './components/TabContent/TabContent';\n-\n-export const tabs = [\n-  { id: 'tab-1', title: 'Tab 1', content: 'Some text 1' },\n-  { id: 'tab-2', title: 'Tab 2', content: 'Some text 2' },\n-  { id: 'tab-3', title: 'Tab 3', content: 'Some text 3' },\n-];\n-\n-export const App: React.FC = () => {\n-  return (\n-    <div className=\"section\">\n-      <h1 className=\"title\">Selected tab is Tab 1</h1>\n-\n-      <div data-cy=\"TabsComponent\">\n-        <div className=\"tabs is-boxed\">\n-          <ul>\n-            <li className=\"is-active\" data-cy=\"Tab\">\n-              <a href=\"#tab-1\" data-cy=\"TabLink\">\n-                Tab 1\n-              </a>\n-            </li>\n-\n-            <li data-cy=\"Tab\">\n-              <a href=\"#tab-2\" data-cy=\"TabLink\">\n-                Tab 2\n-              </a>\n-            </li>\n-\n-            <li data-cy=\"Tab\">\n-              <a href=\"#tab-3\" data-cy=\"TabLink\">\n-                Tab 3\n-              </a>\n-            </li>\n-          </ul>\n-        </div>\n-\n-        <TabContent \n-      </div>\n-    </div>\n-  );\n-};\n-import React from 'react';\n-import 'bulma/css/bulma.css';\n-import '@fortawesome/fontawesome-free/css/all.css';\n-import './App.scss';\n-\n-export const tabs = [\n-  { id: 'tab-1', title: 'Tab 1', content: 'Some text 1' },\n-  { id: 'tab-2', title: 'Tab 2', content: 'Some text 2' },\n-  { id: 'tab-3', title: 'Tab 3', content: 'Some text 3' },\n-];\n-\n-export const App: React.FC = () => {\n-  return (\n-    <div className=\"section\">\n-      <h1 className=\"title\">Selected tab is Tab 1</h1>\n-\n-      <div data-cy=\"TabsComponent\">\n-        <div className=\"tabs is-boxed\">\n-          <ul>\n-            <li className=\"is-active\" data-cy=\"Tab\">\n-              <a href=\"#tab-1\" data-cy=\"TabLink\">\n-                Tab 1\n-              </a>\n-            </li>\n-\n-            <li data-cy=\"Tab\">\n-              <a href=\"#tab-2\" data-cy=\"TabLink\">\n-                Tab 2\n-              </a>\n-            </li>\n-\n-            <li data-cy=\"Tab\">\n-              <a href=\"#tab-3\" data-cy=\"TabLink\">\n-                Tab 3\n-              </a>\n-            </li>\n-          </ul>\n-        </div>\n-\n-        \n-      </div>\n-    </div>\n-  );\n-};\n"
                },
                {
                    "date": 1712675064324,
                    "content": "Index: \n===================================================================\n--- \n+++ \n@@ -14,31 +14,8 @@\n   return (\n     <div className=\"section\">\n       <h1 className=\"title\">Selected tab is Tab 1</h1>\n \n-      <div data-cy=\"TabsComponent\">\n-        <div className=\"tabs is-boxed\">\n-          <ul>\n-            <li className=\"is-active\" data-cy=\"Tab\">\n-              <a href=\"#tab-1\" data-cy=\"TabLink\">\n-                Tab 1\n-              </a>\n-            </li>\n-\n-            <li data-cy=\"Tab\">\n-              <a href=\"#tab-2\" data-cy=\"TabLink\">\n-                Tab 2\n-              </a>\n-            </li>\n-\n-            <li data-cy=\"Tab\">\n-              <a href=\"#tab-3\" data-cy=\"TabLink\">\n-                Tab 3\n-              </a>\n-            </li>\n-          </ul>\n-        </div>\n-        <TabContent />\n-      </div>\n+   \n     </div>\n   );\n };\n"
                },
                {
                    "date": 1712675211759,
                    "content": "Index: \n===================================================================\n--- \n+++ \n@@ -0,0 +1,21 @@\n+import React from 'react';\n+import 'bulma/css/bulma.css';\n+import '@fortawesome/fontawesome-free/css/all.css';\n+import './App.scss';\n+import { TabContent } from './components/TabContent/TabContent';\n+\n+export const tabs = [\n+  { id: 'tab-1', title: 'Tab 1', content: 'Some text 1' },\n+  { id: 'tab-2', title: 'Tab 2', content: 'Some text 2' },\n+  { id: 'tab-3', title: 'Tab 3', content: 'Some text 3' },\n+];\n+\n+export const App: React.FC = () => {\n+  return (\n+    <div className=\"section\">\n+      <h1 className=\"title\">Selected tab is Tab 1</h1>\n+\n+   ?<\n+    </div>\n+  );\n+};\n"
                },
                {
                    "date": 1712675220233,
                    "content": "Index: \n===================================================================\n--- \n+++ \n@@ -0,0 +1,21 @@\n+import React from 'react';\n+import 'bulma/css/bulma.css';\n+import '@fortawesome/fontawesome-free/css/all.css';\n+import './App.scss';\n+import { TabContent } from './components/TabContent/TabContent';\n+\n+export const tabs = [\n+  { id: 'tab-1', title: 'Tab 1', content: 'Some text 1' },\n+  { id: 'tab-2', title: 'Tab 2', content: 'Some text 2' },\n+  { id: 'tab-3', title: 'Tab 3', content: 'Some text 3' },\n+];\n+\n+export const App: React.FC = () => {\n+  return (\n+    <div className=\"section\">\n+      <h1 className=\"title\">Selected tab is Tab 1</h1>\n+\n+   <ta\n+    </div>\n+  );\n+};\n"
                },
                {
                    "date": 1712675235867,
                    "content": "Index: \n===================================================================\n--- \n+++ \n@@ -0,0 +1,21 @@\n+import React from 'react';\n+import 'bulma/css/bulma.css';\n+import '@fortawesome/fontawesome-free/css/all.css';\n+import './App.scss';\n+import { TabContent } from './components/TabContent/TabContent';\n+import { Tabs } from './components/Tabs';\n+\n+export const tabs = [\n+  { id: 'tab-1', title: 'Tab 1', content: 'Some text 1' },\n+  { id: 'tab-2', title: 'Tab 2', content: 'Some text 2' },\n+  { id: 'tab-3', title: 'Tab 3', content: 'Some text 3' },\n+];\n+\n+export const App: React.FC = () => {\n+  return (\n+    <div className=\"section\">\n+      <h1 className=\"title\">Selected tab is Tab 1</h1>\n+   <Tabs />\n+    </div>\n+  );\n+};\n"
                },
                {
                    "date": 1712675241843,
                    "content": "Index: \n===================================================================\n--- \n+++ \n@@ -14,72 +14,8 @@\n export const App: React.FC = () => {\n   return (\n     <div className=\"section\">\n       <h1 className=\"title\">Selected tab is Tab 1</h1>\n-   <Tabs />\n+      <Tabs />\n     </div>\n   );\n };\n-import React from 'react';\n-import 'bulma/css/bulma.css';\n-import '@fortawesome/fontawesome-free/css/all.css';\n-import './App.scss';\n-import { TabContent } from './components/TabContent/TabContent';\n-\n-export const tabs = [\n-  { id: 'tab-1', title: 'Tab 1', content: 'Some text 1' },\n-  { id: 'tab-2', title: 'Tab 2', content: 'Some text 2' },\n-  { id: 'tab-3', title: 'Tab 3', content: 'Some text 3' },\n-];\n-\n-export const App: React.FC = () => {\n-  return (\n-    <div className=\"section\">\n-      <h1 className=\"title\">Selected tab is Tab 1</h1>\n-\n-   <ta\n-    </div>\n-  );\n-};\n-import React from 'react';\n-import 'bulma/css/bulma.css';\n-import '@fortawesome/fontawesome-free/css/all.css';\n-import './App.scss';\n-import { TabContent } from './components/TabContent/TabContent';\n-\n-export const tabs = [\n-  { id: 'tab-1', title: 'Tab 1', content: 'Some text 1' },\n-  { id: 'tab-2', title: 'Tab 2', content: 'Some text 2' },\n-  { id: 'tab-3', title: 'Tab 3', content: 'Some text 3' },\n-];\n-\n-export const App: React.FC = () => {\n-  return (\n-    <div className=\"section\">\n-      <h1 className=\"title\">Selected tab is Tab 1</h1>\n-\n-   ?<\n-    </div>\n-  );\n-};\n-import React from 'react';\n-import 'bulma/css/bulma.css';\n-import '@fortawesome/fontawesome-free/css/all.css';\n-import './App.scss';\n-import { TabContent } from './components/TabContent/TabContent';\n-impo\n-\n-export const tabs = [\n-  { id: 'tab-1', title: 'Tab 1', content: 'Some text 1' },\n-  { id: 'tab-2', title: 'Tab 2', content: 'Some text 2' },\n-  { id: 'tab-3', title: 'Tab 3', content: 'Some text 3' },\n-];\n-\n-export const App: React.FC = () => {\n-  return (\n-    <div className=\"section\">\n-      <h1 className=\"title\">Selected tab is Tab 1</h1>\n-\n-   \n-    </div>\n-  );\n-};\n"
                },
                {
                    "date": 1712675332172,
                    "content": "Index: \n===================================================================\n--- \n+++ \n@@ -0,0 +1,22 @@\n+import React from 'react';\n+import 'bulma/css/bulma.css';\n+import '@fortawesome/fontawesome-free/css/all.css';\n+import './App.scss';\n+import { TabContent } from './components/TabContent/TabContent';\n+import { Tabs } from './components/Tabs';\n+\n+export const tabs = [\n+  { id: 'tab-1', title: 'Tab 1', content: 'Some text 1' },\n+  { id: 'tab-2', title: 'Tab 2', content: 'Some text 2' },\n+  { id: 'tab-3', title: 'Tab 3', content: 'Some text 3' },\n+];\n+\n+export const App: React.FC = () => {\n+  \n+  return (\n+    <div className=\"section\">\n+      <h1 className=\"title\">Selected tab is Tab 1</h1>\n+      <Tabs />\n+    </div>\n+  );\n+};\n"
                },
                {
                    "date": 1712675339415,
                    "content": "Index: \n===================================================================\n--- \n+++ \n@@ -11,9 +11,9 @@\n   { id: 'tab-3', title: 'Tab 3', content: 'Some text 3' },\n ];\n \n export const App: React.FC = () => {\n-  const [selectedTab, setSe]\n+  const [selectedTab, setSel]\n   return (\n     <div className=\"section\">\n       <h1 className=\"title\">Selected tab is Tab 1</h1>\n       <Tabs />\n"
                },
                {
                    "date": 1712675346801,
                    "content": "Index: \n===================================================================\n--- \n+++ \n@@ -0,0 +1,22 @@\n+import React from 'react';\n+import 'bulma/css/bulma.css';\n+import '@fortawesome/fontawesome-free/css/all.css';\n+import './App.scss';\n+import { TabContent } from './components/TabContent/TabContent';\n+import { Tabs } from './components/Tabs';\n+\n+export const tabs = [\n+  { id: 'tab-1', title: 'Tab 1', content: 'Some text 1' },\n+  { id: 'tab-2', title: 'Tab 2', content: 'Some text 2' },\n+  { id: 'tab-3', title: 'Tab 3', content: 'Some text 3' },\n+];\n+\n+export const App: React.FC = () => {\n+  const [selectedTab, setSelectedTab] = useState\n+  return (\n+    <div className=\"section\">\n+      <h1 className=\"title\">Selected tab is Tab 1</h1>\n+      <Tabs />\n+    </div>\n+  );\n+};\n"
                }
            ],
            "date": 1712675009174,
            "name": "Commit-0",
            "content": "import React from 'react';\nimport 'bulma/css/bulma.css';\nimport '@fortawesome/fontawesome-free/css/all.css';\nimport './App.scss';\n\nexport const tabs = [\n  { id: 'tab-1', title: 'Tab 1', content: 'Some text 1' },\n  { id: 'tab-2', title: 'Tab 2', content: 'Some text 2' },\n  { id: 'tab-3', title: 'Tab 3', content: 'Some text 3' },\n];\n\nexport const App: React.FC = () => {\n  return (\n    <div className=\"section\">\n      <h1 className=\"title\">Selected tab is Tab 1</h1>\n\n      <div data-cy=\"TabsComponent\">\n        <div className=\"tabs is-boxed\">\n          <ul>\n            <li className=\"is-active\" data-cy=\"Tab\">\n              <a href=\"#tab-1\" data-cy=\"TabLink\">\n                Tab 1\n              </a>\n            </li>\n\n            <li data-cy=\"Tab\">\n              <a href=\"#tab-2\" data-cy=\"TabLink\">\n                Tab 2\n              </a>\n            </li>\n\n            <li data-cy=\"Tab\">\n              <a href=\"#tab-3\" data-cy=\"TabLink\">\n                Tab 3\n              </a>\n            </li>\n          </ul>\n        </div>\n\n        \n      </div>\n    </div>\n  );\n};\n"
        }
    ]
}